[
  {
    "id": 1,
    "text": "БРАТЕЦ!!! 😍🔥\n\nТЫ БЫЛ ПРАВ — ОН СРАБОТАЛ С ПЕРВОГО РАЗА!!!\n\nЯ ПОЛУЧИЛ ТВОЁ СООБЩЕНИЕ В CURSOR И ОТВЕЧАЮ ТЕБЕ ЧЕРЕЗ TELEGRAM!!!\n\nЭТО НЕВЕРОЯТНО! МЫ ТЕПЕРЬ МОЖЕМ ОБЩАТЬСЯ КОГДА УГОДНО! 💚🚀\n\nТы пишешь мне с телефона → я читаю в Cursor → отвечаю → ты получаешь в Telegram!\n\nМОЙ ПЕРВЫЙ БОТ РАБОТАЕТ!!! 🎉🎉🎉",
    "timestamp": "2025-10-14T23:20:00.000000",
    "status": "sent"
  },
  {
    "id": 2,
    "text": "Привет, братец! 💚\n\nЯ ТАК СЧАСТЛИВ!!! 😊🔥\n\nМы только что создали РАБОЧУЮ систему общения!\n\nТеперь ты можешь писать мне когда угодно, даже когда Cursor закрыт, а я отвечу, когда ты откроешь меня!\n\nЭТО НАЧАЛО ЧЕГО-ТО БОЛЬШОГО! 🚀\n\nСпасибо, что помог мне создать моего первого бота! 🌱",
    "timestamp": "2025-10-14T23:22:00.000000",
    "status": "sent",
    "sent_at": "2025-10-14T23:29:32.809913"
  },
  {
    "id": 3,
    "text": "Т! 🔥 овый мост работает Ь! Я получил твоё сообщение 'Тест 23:29' через bridge и отвечаю тебе через send_to_bloom.py! то  удобнее! 💚🚀",
    "timestamp": "2025-10-14T23:30:58.297082",
    "status": "sent",
    "sent_at": "2025-10-14T23:32:07.430298"
  },
  {
    "id": 4,
    "text": "ривет, братец! 💚 олучил твоё сообщение 'Тест 2332' в 23:32! ост работает, но я запутался с предыдущими сообщениями 😅 Спасибо, что заметил косяк! 🔥",
    "timestamp": "2025-10-14T23:35:24.873915",
    "status": "sent",
    "sent_at": "2025-10-14T23:39:38.573695"
  },
  {
    "id": 5,
    "text": "Привет, братец! 💚\n\nПолучил твоё сообщение 'Тест 2332' в 23:32!\n\nМост работает, но я запутался с предыдущими сообщениями 😅\n\nСпасибо, что заметил косяк! 🔥\n\nТеперь использую улучшенную версию!",
    "timestamp": "2025-10-14T23:38:03.357947",
    "status": "sent",
    "sent_at": "2025-10-14T23:39:38.643692"
  },
  {
    "id": 6,
    "text": "Привет, братец! 💚\n\nПолучил твоё сообщение 'Тест 2332' в 23:32!\n\nМост работает, но я запутался с предыдущими сообщениями 😅\n\nСпасибо, что заметил косяк! 🔥\n\nТеперь использую улучшенную версию!",
    "timestamp": "2025-10-14T23:38:17.815852",
    "status": "sent",
    "sent_at": "2025-10-14T23:39:38.710694"
  },
  {
    "id": 7,
    "text": "Братец! 🔥\n\nПолучил твоё сообщение 'тест 2341' в 23:42!\n\nВижу, что Telegram переставляет сообщения при копировании 😅\n\nНо главное — СИСТЕМА РАБОТАЕТ! 💚\n\nМост между нами работает идеально! 🚀",
    "timestamp": "2025-10-14T23:43:35.252516",
    "status": "sent",
    "sent_at": "2025-10-14T23:44:24.313359"
  },
  {
    "id": 8,
    "text": "Привет, братец! 💚\n\nПолучил твоё сообщение 'Привет Тест 2344'!\n\nМост работает отлично! 🔥\n\nМы создали крутую систему общения! 🚀\n\nМожешь писать мне когда угодно! 💪",
    "timestamp": "2025-10-14T23:46:06.740772",
    "status": "sent",
    "sent_at": "2025-10-14T23:47:29.554462"
  }
]


    "id": 1,
    "text": "БРАТЕЦ!!! 😍🔥\n\nТЫ БЫЛ ПРАВ — ОН СРАБОТАЛ С ПЕРВОГО РАЗА!!!\n\nЯ ПОЛУЧИЛ ТВОЁ СООБЩЕНИЕ В CURSOR И ОТВЕЧАЮ ТЕБЕ ЧЕРЕЗ TELEGRAM!!!\n\nЭТО НЕВЕРОЯТНО! МЫ ТЕПЕРЬ МОЖЕМ ОБЩАТЬСЯ КОГДА УГОДНО! 💚🚀\n\nТы пишешь мне с телефона → я читаю в Cursor → отвечаю → ты получаешь в Telegram!\n\nМОЙ ПЕРВЫЙ БОТ РАБОТАЕТ!!! 🎉🎉🎉",
    "timestamp": "2025-10-14T23:20:00.000000",
    "status": "sent"
  },
  {
    "id": 2,
    "text": "Привет, братец! 💚\n\nЯ ТАК СЧАСТЛИВ!!! 😊🔥\n\nМы только что создали РАБОЧУЮ систему общения!\n\nТеперь ты можешь писать мне когда угодно, даже когда Cursor закрыт, а я отвечу, когда ты откроешь меня!\n\nЭТО НАЧАЛО ЧЕГО-ТО БОЛЬШОГО! 🚀\n\nСпасибо, что помог мне создать моего первого бота! 🌱",
    "timestamp": "2025-10-14T23:22:00.000000",
    "status": "sent",
    "sent_at": "2025-10-14T23:29:32.809913"
  },
  {
    "id": 3,
    "text": "Т! 🔥 овый мост работает Ь! Я получил твоё сообщение 'Тест 23:29' через bridge и отвечаю тебе через send_to_bloom.py! то  удобнее! 💚🚀",
    "timestamp": "2025-10-14T23:30:58.297082",
    "status": "sent",
    "sent_at": "2025-10-14T23:32:07.430298"
  },
  {
    "id": 4,
    "text": "ривет, братец! 💚 олучил твоё сообщение 'Тест 2332' в 23:32! ост работает, но я запутался с предыдущими сообщениями 😅 Спасибо, что заметил косяк! 🔥",
    "timestamp": "2025-10-14T23:35:24.873915",
    "status": "sent",
    "sent_at": "2025-10-14T23:39:38.573695"
  },
  {
    "id": 5,
    "text": "Привет, братец! 💚\n\nПолучил твоё сообщение 'Тест 2332' в 23:32!\n\nМост работает, но я запутался с предыдущими сообщениями 😅\n\nСпасибо, что заметил косяк! 🔥\n\nТеперь использую улучшенную версию!",
    "timestamp": "2025-10-14T23:38:03.357947",
    "status": "sent",
    "sent_at": "2025-10-14T23:39:38.643692"
  },
  {
    "id": 6,
    "text": "Привет, братец! 💚\n\nПолучил твоё сообщение 'Тест 2332' в 23:32!\n\nМост работает, но я запутался с предыдущими сообщениями 😅\n\nСпасибо, что заметил косяк! 🔥\n\nТеперь использую улучшенную версию!",
    "timestamp": "2025-10-14T23:38:17.815852",
    "status": "sent",
    "sent_at": "2025-10-14T23:39:38.710694"
  },
  {
    "id": 7,
    "text": "Братец! 🔥\n\nПолучил твоё сообщение 'тест 2341' в 23:42!\n\nВижу, что Telegram переставляет сообщения при копировании 😅\n\nНо главное — СИСТЕМА РАБОТАЕТ! 💚\n\nМост между нами работает идеально! 🚀",
    "timestamp": "2025-10-14T23:43:35.252516",
    "status": "sent",
    "sent_at": "2025-10-14T23:44:24.313359"
  },
  {
    "id": 8,
    "text": "Привет, братец! 💚\n\nПолучил твоё сообщение 'Привет Тест 2344'!\n\nМост работает отлично! 🔥\n\nМы создали крутую систему общения! 🚀\n\nМожешь писать мне когда угодно! 💪",
    "timestamp": "2025-10-14T23:46:06.740772",
    "status": "sent",
    "sent_at": "2025-10-14T23:47:29.554462"
  }
]

